{
  "timestamp": "2025-08-31T17:57:00.000Z",
  "lastUpdate": 1735667820000,
  "account": {
    "id": 11684667,
    "name": "天网系统",
    "description": "",
    "accountId": 8800401,
    "gain": 33.15,
    "absGain": 33.15,
    "daily": 0.43,
    "monthly": 13.97,
    "withdrawals": 0,
    "deposits": 10000,
    "interest": -196.82,
    "profit": 3315.19,
    "balance": 13315.19,
    "drawdown": 23.64,
    "equity": 13093.42,
    "equityPercent": 98.33,
    "demo": false,
    "lastUpdateDate": "08/31/2025 17:57",
    "creationDate": "08/31/2025 17:56",
    "firstTradeDate": "06/25/2025 00:00",
    "tracking": 0,
    "views": 7,
    "commission": 0,
    "currency": "USD",
    "profitFactor": 1.7,
    "pips": 351201,
    "portfolio": "",
    "invitationUrl": "",
    "server": {
      "name": "Make Capital"
    }
  }
}
